Metadata-Version: 2.1
Name: searchft
Version: 0.0.6
Summary: Projeto final da disciplina de Programação Orientada a Objetos II
Author: liedson
Author-email: fabricoliedson@gamil.com
Keywords: python,web,search
Classifier: Development Status :: 3 - Alpha
Classifier: Intended Audience :: Education
Classifier: Programming Language :: Python :: 3
License-File: LICENSE
